xiaoshiai_hub/__init__.py
xiaoshiai_hub/auth.py
xiaoshiai_hub/cli.py
xiaoshiai_hub/client.py
xiaoshiai_hub/download.py
xiaoshiai_hub/envelope_crypto.py
xiaoshiai_hub/exceptions.py
xiaoshiai_hub/types.py
xiaoshiai_hub/upload.py
xiaoshiai_hub-1.1.3.dist-info/licenses/LICENSE
xiaoshiai_hub-1.1.3.dist-info/METADATA
xiaoshiai_hub-1.1.3.dist-info/WHEEL
xiaoshiai_hub-1.1.3.dist-info/entry_points.txt
xiaoshiai_hub-1.1.3.dist-info/top_level.txt
xiaoshiai_hub-1.1.3.dist-info/RECORD
