Metadata-Version: 2.4
Name: xiaoshiai-hub
Version: 1.1.3
Summary: Python SDK for XiaoShi AI Hub - Upload, download, and manage AI models and datasets with xpai-enc encryption support
Home-page: https://github.com/poxiaoyun/moha-sdk
Author: XiaoShi AI
Author-email: XiaoShi AI <support@xiaoshiai.cn>
Maintainer: XiaoShi AI Team
Maintainer-email: XiaoShi AI Team <support@xiaoshiai.cn>
License: Apache-2.0
Project-URL: Homepage, https://github.com/poxiaoyun/moha-sdk
Project-URL: Repository, https://github.com/poxiaoyun/moha-sdk
Project-URL: Issues, https://github.com/poxiaoyun/moha-sdk/issues
Keywords: xiaoshi,ai-hub,machine-learning,deep-learning,model-hub,dataset,encryption,xpai-enc,sdk,api-client,model-encryption
Classifier: Development Status :: 4 - Beta
Classifier: Intended Audience :: Developers
Classifier: Intended Audience :: Science/Research
Classifier: Topic :: Software Development :: Libraries :: Python Modules
Classifier: Topic :: Scientific/Engineering :: Artificial Intelligence
Classifier: License :: OSI Approved :: Apache Software License
Classifier: Operating System :: OS Independent
Classifier: Programming Language :: Python :: 3
Classifier: Programming Language :: Python :: 3.7
Classifier: Programming Language :: Python :: 3.8
Classifier: Programming Language :: Python :: 3.9
Classifier: Programming Language :: Python :: 3.10
Classifier: Programming Language :: Python :: 3.11
Classifier: Programming Language :: Python :: 3 :: Only
Requires-Python: >=3.7
License-File: LICENSE
Requires-Dist: requests>=2.20.0
Requires-Dist: tqdm>=4.62.0
Provides-Extra: upload
Requires-Dist: gitpython>=3.1.0; extra == "upload"
Provides-Extra: encryption
Provides-Extra: dev
Requires-Dist: pytest>=6.0; extra == "dev"
Requires-Dist: pytest-cov>=2.0; extra == "dev"
Requires-Dist: pytest-mock>=3.6.0; extra == "dev"
Requires-Dist: black>=22.0; extra == "dev"
Requires-Dist: flake8>=4.0; extra == "dev"
Requires-Dist: mypy>=0.950; extra == "dev"
Requires-Dist: isort>=5.10.0; extra == "dev"
Requires-Dist: build>=0.8.0; extra == "dev"
Requires-Dist: twine>=4.0.0; extra == "dev"
Requires-Dist: gitpython>=3.1.0; extra == "dev"
Provides-Extra: all
Requires-Dist: gitpython>=3.1.0; extra == "all"
Dynamic: author
Dynamic: home-page
Dynamic: license-file
Dynamic: maintainer
Dynamic: requires-python
